ctplanet/Hydrostatic.py
ctplanet/InertiaTensor.py
ctplanet/Moho.py
ctplanet/ReadRefModel.py
ctplanet/__init__.py
ctplanet/_version.py
ctplanet-0.2.15.dist-info/LICENSE.txt
ctplanet-0.2.15.dist-info/METADATA
ctplanet-0.2.15.dist-info/WHEEL
ctplanet-0.2.15.dist-info/top_level.txt
ctplanet-0.2.15.dist-info/RECORD
