Metadata-Version: 2.1
Name: ctplanet
Version: 0.2.15
Summary: Create a crustal thickness map of a planet
Author-email: Mark Wieczorek <mark.wieczorek@ipgp.fr>
License: BSD-3-Clause
Project-URL: homepage, https://github.com/MarkWieczorek/ctplanet
Project-URL: download, https://github.com/MarkWieczorek/ctplanet/zipball/master
Keywords: crust,gravity,geophysics
Classifier: Development Status :: 3 - Alpha
Classifier: Environment :: Console
Classifier: Intended Audience :: Science/Research
Classifier: Intended Audience :: Developers
Classifier: License :: OSI Approved :: BSD License
Classifier: Natural Language :: English
Classifier: Operating System :: OS Independent
Classifier: Programming Language :: Python
Classifier: Programming Language :: Python :: 3
Classifier: Topic :: Scientific/Engineering :: Physics
Classifier: Topic :: Scientific/Engineering
Requires-Python: >=3.8
License-File: LICENSE.txt
Requires-Dist: pyshtools>=4.13.1
